{
    "pageNumber": 0,
    "data": [
        {
            "id": "117404135",
            "title": "Astralasia - Seven Pointed Star (Full Version)",
            "date_created": "1505334106",
            "loginId": "1758397",
            "tags": null,
            "description": "psy trance.",
            "asset": {
                "type": "youtube",
                "author": "waldvolk",
                "hdvFlag": 0,
                "description": "psy trance.",
                "tags": "",
                "thumbnailUrl": "https:\/\/i.ytimg.com\/vi\/lgZPF_l6g6A\/hqdefault.jpg",
                "videoId": "lgZPF_l6g6A",
                "mediaDuration": 403,
                "prettyDuration": "00:06:43"
            },
            "parentId": "117406393",
            "url": "\/9\/astralasia-seven-pointed-star-full-version\/117406393-117404135"
        }
    ]
}